{"data_mtime": 1669350735, "dep_lines": [14, 26, 15, 16, 25, 1, 3, 15, 1, 1, 1, 1, 1, 1, 1, 1, 1, 1, 21, 22], "dep_prios": [5, 25, 10, 5, 25, 5, 5, 20, 5, 30, 30, 30, 30, 30, 30, 30, 30, 30, 25, 25], "dependencies": ["alembic.runtime.migration", "alembic.script.base", "alembic.util", "alembic.operations", "alembic.config", "__future__", "typing", "alembic", "builtins", "_typeshed", "abc", "alembic.operations.base", "alembic.operations.batch", "alembic.script", "alembic.util.exc", "alembic.util.langhelpers", "argparse", "contextlib"], "hash": "5a09e6acf84b189810a59299f0a6a32e7d39678796b58cca1f24a2390dbcb4cd", "id": "alembic.runtime.environment", "ignore_all": true, "interface_hash": "4779ce81d43a1cddb5ef26ca2b1073eaaa5273ead99b9c68b810bb1b94454843", "mtime": 1669350684, "options": {"allow_redefinition": false, "allow_untyped_globals": false, "always_false": [], "always_true": [], "bazel": false, "check_untyped_defs": false, "disable_bytearray_promotion": false, "disable_error_code": [], "disable_memoryview_promotion": false, "disabled_error_codes": [], "disallow_any_decorated": false, "disallow_any_explicit": false, "disallow_any_expr": false, "disallow_any_generics": false, "disallow_any_unimported": false, "disallow_incomplete_defs": false, "disallow_subclassing_any": false, "disallow_untyped_calls": false, "disallow_untyped_decorators": false, "disallow_untyped_defs": false, "enable_error_code": [], "enabled_error_codes": [], "follow_imports": "silent", "follow_imports_for_stubs": false, "ignore_errors": false, "ignore_missing_imports": true, "implicit_optional": false, "implicit_reexport": true, "local_partial_types": false, "mypyc": false, "platform": "win32", "plugins": [], "strict_concatenate": false, "strict_equality": false, "strict_optional": true, "warn_no_return": true, "warn_return_any": false, "warn_unreachable": false, "warn_unused_ignores": false}, "path": "c:\\Users\\user\\OneDrive\\\u684c\u9762\\\u7a0b\u5f0f\u8a9e\u8a00\\Fastapi1\\Fast API\\venv\\lib\\site-packages\\alembic\\runtime\\environment.py", "plugin_data": null, "size": 38560, "suppressed": ["sqlalchemy.engine.base", "sqlalchemy.sql.schema"], "version_id": "0.991"}